google/cloud/cloudquotas/__init__.py
google/cloud/cloudquotas/gapic_version.py
google/cloud/cloudquotas/py.typed
google/cloud/cloudquotas_v1/__init__.py
google/cloud/cloudquotas_v1/gapic_metadata.json
google/cloud/cloudquotas_v1/gapic_version.py
google/cloud/cloudquotas_v1/py.typed
google/cloud/cloudquotas_v1/services/__init__.py
google/cloud/cloudquotas_v1/services/cloud_quotas/__init__.py
google/cloud/cloudquotas_v1/services/cloud_quotas/async_client.py
google/cloud/cloudquotas_v1/services/cloud_quotas/client.py
google/cloud/cloudquotas_v1/services/cloud_quotas/pagers.py
google/cloud/cloudquotas_v1/services/cloud_quotas/transports/__init__.py
google/cloud/cloudquotas_v1/services/cloud_quotas/transports/base.py
google/cloud/cloudquotas_v1/services/cloud_quotas/transports/grpc.py
google/cloud/cloudquotas_v1/services/cloud_quotas/transports/grpc_asyncio.py
google/cloud/cloudquotas_v1/services/cloud_quotas/transports/rest.py
google/cloud/cloudquotas_v1/services/cloud_quotas/transports/rest_base.py
google/cloud/cloudquotas_v1/types/__init__.py
google/cloud/cloudquotas_v1/types/cloudquotas.py
google/cloud/cloudquotas_v1/types/resources.py
google/cloud/cloudquotas_v1beta/__init__.py
google/cloud/cloudquotas_v1beta/gapic_metadata.json
google/cloud/cloudquotas_v1beta/gapic_version.py
google/cloud/cloudquotas_v1beta/py.typed
google/cloud/cloudquotas_v1beta/services/__init__.py
google/cloud/cloudquotas_v1beta/services/cloud_quotas/__init__.py
google/cloud/cloudquotas_v1beta/services/cloud_quotas/async_client.py
google/cloud/cloudquotas_v1beta/services/cloud_quotas/client.py
google/cloud/cloudquotas_v1beta/services/cloud_quotas/pagers.py
google/cloud/cloudquotas_v1beta/services/cloud_quotas/transports/__init__.py
google/cloud/cloudquotas_v1beta/services/cloud_quotas/transports/base.py
google/cloud/cloudquotas_v1beta/services/cloud_quotas/transports/grpc.py
google/cloud/cloudquotas_v1beta/services/cloud_quotas/transports/grpc_asyncio.py
google_cloud_quotas-0.4.0.dist-info/licenses/LICENSE
google_cloud_quotas-0.4.0.dist-info/METADATA
google_cloud_quotas-0.4.0.dist-info/WHEEL
google_cloud_quotas-0.4.0.dist-info/top_level.txt
google_cloud_quotas-0.4.0.dist-info/RECORD
